{"noMoreComments": true, "cursorEnd": 0, "id": "3578840", "comments": [{"postBy": {"location": "\u53f0\u4e2d\u5e02\u00b7\u53f0\u7063", "utc": 1461912611000, "level": 0, "avatar": "http://filestoresg1.beetalkmobile.com:8081/file/-2744891195183037045", "name": "\u5ed6\u5065\u7a0b"}, "content": "\u5e7e\u5e74\uff0c\u8f4eor\u8ca8\u7248\uff0c\u8ce3\u591a\u5c11\uff1f", "urls": [], "replies": {"first": [{"content": "05\u5e74 \u8f4e\u8eca\u7248  \u8eca\u50f917.8, ", "reply": "", "id": 24354678, "name": "\u5889\u4ed4"}], "last": [{"content": "\u4f60\u8981\u627e\u8eca\u5b50\u55ce\uff1f", "reply": "", "id": 24354985, "name": "\u5889\u4ed4"}, {"content": "\u53c3\u8003\u770b\u770b\u800c\u5df2\uff5e", "reply": "", "id": 24361053, "name": "\u5ed6\u5065\u7a0b"}], "noMoreReplies": true}, "images": [], "id": 37692820}]}
