{"noMoreComments": true, "cursorEnd": 0, "id": "3135928", "comments": [{"postBy": {"location": "\u53f0\u6771\u7e23\u00b7\u53f0\u7063", "utc": 1455891125000, "level": 0, "avatar": "http://filestoresg1.beetalkmobile.com:8081/file/5509883678323691202", "name": "\u79c9\u5b8f"}, "content": "\u770b\u8d77\u4f86\u79c0\u8272\u53ef\u9910\u55b2\uff01\u9019\u9ebc\u6703\u716e\u7684\u5973\u5b69\u4e00\u5b9a\u5f88\u6436\u624b\u3002", "urls": [], "replies": {"first": [], "last": [], "noMoreReplies": true}, "images": [], "id": 32030903}, {"postBy": {"location": "\u53f0\u5317\u5e02\u00b7\u53f0\u7063", "utc": 1455916294000, "level": 0, "avatar": "http://filestoresg1.beetalkmobile.com:8081/file/-5542718373910418627", "name": "\u9589\u95dc\u4e2d"}, "content": "\u770b\u8d77\u4f86\u4e0d\u932f\u3002<br /><br />\u6750\u6599\u505a\u6cd5\u5462?(\u4f38)", "urls": [], "replies": {"first": [], "last": [], "noMoreReplies": true}, "images": [], "id": 32053511}, {"postBy": {"location": "\u6843\u5712\u5e02\u00b7\u53f0\u7063", "utc": 1455927731000, "level": 0, "avatar": "http://filestoresg1.beetalkmobile.com:8081/file/-1052132560499645527", "name": "\ud83d\ude11Annalita Chen"}, "content": "\u849c\u82d7\uff0c\u8525\u52a0\u5206!!!^_^", "urls": [], "replies": {"first": [], "last": [], "noMoreReplies": true}, "images": [], "id": 32058130}, {"postBy": {"location": "\u6843\u5712\u5e02\u00b7\u53f0\u7063", "utc": 1456065414000, "level": 0, "avatar": "http://filestoresg1.beetalkmobile.com:8081/file/3502279888048041431", "name": "\u738b\u5b50\u96f2-\u63f4\u4ea4\u52ff\u7169\u8b1d\u8b1d"}, "content": "\u770b\u8d77\u4f86\u4e0d\u932f\u5403\uff0c<br />\u8981\u662f\u60f3\u63db\u5370\u5ea6\u53e3\u5473\u653e\u5496\u55b1\uff0c<br />\u60f3\u5403\u97d3\u5f0f\u653e\u8fa3\u6ce1\u83dc\uff0c<br />\u4e2d\u570b\u5f0f\u653e\u4e94\u9999\u7c89\uff0c<br />\u60f3\u5403\u975e\u6d32\u5f0f\u653e\u6ce5\u571f<\u9019\u62db\u662f\u4f86\u4e82\u5225\u771f\u7684\u5690\u8a66", "urls": [], "replies": {"first": [], "last": [], "noMoreReplies": true}, "images": [], "id": 32194915}, {"postBy": {"location": "\u53f0\u4e2d\u5e02\u00b7\u53f0\u7063", "utc": 1457117600000, "level": 0, "avatar": "http://filestoresg1.beetalkmobile.com:8081/file/770111153177451635", "name": "\u984f\u6749\u745e"}, "content": "\u9032\u7684\u4e86\u5eda\u623f\uff0c\u53ef\u4ee5\u5ac1\u4eba\u4e86", "urls": [], "replies": {"first": [], "last": [], "noMoreReplies": true}, "images": ["http://filestoresg1.beetalkmobile.com:8081/file/1196475f678cc1302607e3cb7c0ca67b"], "id": 33156624}, {"postBy": {"location": "\u53f0\u4e2d\u5e02\u00b7\u53f0\u7063", "utc": 1457143215000, "level": 0, "avatar": "http://filestoresg1.beetalkmobile.com:8081/file/-2603859025037119178", "name": "\u6708\u4f11\u534a\u500b\u6708"}, "content": "\u62cc\u9ede\u8fa3\u8c46\u74e3\u91ac\u66f4\u63d0\u5473 \ud83d\ude0b", "urls": [], "replies": {"first": [], "last": [], "noMoreReplies": true}, "images": [], "id": 33168578}, {"postBy": {"location": "\u65b0\u5317\u5e02\u00b7\u53f0\u7063", "utc": 1457178231000, "level": 0, "avatar": "http://filestoresg1.beetalkmobile.com:8081/file/1", "name": "\u8d85\u60e1\u7537\u5b50"}, "content": "\u6211\u716e\u6ce1\u9eb5\u4e5f\u8d0f\u59b3", "urls": [], "replies": {"first": [], "last": [], "noMoreReplies": true}, "images": [], "id": 33202269}]}
