{"noMoreComments": true, "cursorEnd": 0, "id": "3117762", "comments": [{"postBy": {"location": "\u9ad8\u96c4\u5e02\u00b7\u53f0\u7063", "utc": 1455645072000, "level": 0, "avatar": "http://filestoresg1.beetalkmobile.com:8081/file/1692909258541679104", "name": "\u5c0f\u9b5a\ud83d\udc1f"}, "content": "\u591a\u591a\u6e9d\u901a<br />\u7121\u6cd5\u6e9d\u901a\u5c31\u653e\u624b\u5427<br />\u6c92\u6709\u514b\u670d\u4e0d\u4e86\u7684\u4e8b<br />\u53ea\u6709\u4e0d\u60f3\u514b\u670d\u7684\u4eba", "urls": [], "replies": {"first": [], "last": [], "noMoreReplies": true}, "images": [], "id": 31812438}, {"postBy": {"location": "\u65b0\u5317\u5e02\u00b7\u53f0\u7063", "utc": 1455646469000, "level": 0, "avatar": "http://filestoresg1.beetalkmobile.com:8081/file/-3305162732300567173", "name": "\u91d1\u7cfb173"}, "content": "\u5982\u679c\u59b3\u60f3\u8981\u611b\u60c5\u5c31\u653e\u624b\u53bb<br />\u4e8c\u4f86\u5982\u679c\u59b3\u5bb3\u6015\u5c31\u6c38\u9060\u4e00\u500b\u4eba  \u751a\u81f3\u932f\u904e<br />\u78ba\u5b9a\u4e4b\u5f8c\u53ef\u4ee5\u597d\u597d\u53bb\u8a8d\u8b58\u8ac7\u5410\u4e00\u4e0b<br />\u597d\u597d\u60f3\u60f3\u5427", "urls": [], "replies": {"first": [{"content": "\u662f\u554a\u22ef\u6211\u771f\u7684\u5f88\u5bb9\u6613\u602f\u6b65\u22ef\ud83d\ude05", "reply": "", "id": 20410374, "name": "\u5c0f\u51b7"}, {"content": "\u52a0\u59b3\u804a\u5929\u4e00\u4e0b\u5427", "reply": "\u5c0f\u51b7", "id": 20410389, "name": "\u91d1\u7cfb173"}], "last": [], "noMoreReplies": true}, "images": [], "id": 31813485}, {"postBy": {"location": "\u65b0\u7af9\u5e02\u00b7\u53f0\u7063", "utc": 1455759052000, "level": 0, "avatar": "http://filestoresg1.beetalkmobile.com:8081/file/4178925939522944901", "name": "\ud83c\udf51"}, "content": "\u5176\u5be6\u6211\u89ba\u5f97\u5e74\u9f61\u4e0d\u662f\u554f\u984c<br />\u7576\u4f60\u611b\u5230\u4e86<br />\u624d\u4e0d\u6703\u7ba1\u4ec0\u9ebc\u5e74\u7d00\u554f\u984c\u5462\u3002<br /><br />\u81f3\u65bc\u59b3\u6240\u60f3\u7684\u90a3\u4e9b<br />\u90fd\u662f\u4e8b\u5be6\u4e5f\u662f\u73fe\u5be6<br />\u59b3\u9078\u64c7\u63a5\u53d7<br />\u5c31\u4e0d\u8981\u5f8c\u6094\u3002<br /><br />\u7576\u7136\u4e5f\u4e0d\u662f\u6bcf\u500b\u9bae\u8089\u90fd\u9019\u9ebc\u4e0d\u7a69<br />\u9084\u662f\u6709\u883b\u591a\u6210\u719f\u60f3\u6cd5\u7684\u9bae\u8089\u5566\uff01", "urls": [], "replies": {"first": [{"content": "\u5c31\u662f\u6015\u5f1f\u5f1f\u6703\u592a\u5584\u8b8a\u22ef\u6211\u6703\u53d7\u50b7\u22ef\u4f46\u6211\u73fe\u5728\u559c\u6b61\u7684\u90fd\u662f\u5e74\u7d00\u5c0f\u7684\u22ef\u22ef\u670b\u53cb\u8aaa\u6211\u5e74\u7d00\u9577\u4e86\uff0c\u8166\u5b50\u6c92\u9577\ud83d\ude05\u96e3\u9053\u5973\u751f\u53ea\u53ef\u4ee5\u4ea4\u5e74\u7d00\u5927\u7684\u55ce", "reply": "", "id": 20492819, "name": "\u5c0f\u51b7"}], "last": [], "noMoreReplies": true}, "images": [], "id": 31905329}, {"postBy": {"location": "\u5357\u6295\u7e23\u00b7\u53f0\u7063", "utc": 1455760044000, "level": 0, "avatar": "http://filestoresg1.beetalkmobile.com:8081/file/658589888961532417", "name": "\u6d41\u7a7a\u81ea\u7531"}, "content": "\u611f\u60c5\u53ea\u6709\u9858\u4e0d\u9858\u610f\u3002\u6c92\u6709\u5176\u4ed6\u56e0\u7d20\u3002\u60f3\u592a\u591a\u4e86", "urls": [], "replies": {"first": [], "last": [], "noMoreReplies": true}, "images": [], "id": 31906075}, {"postBy": {"location": "\u53f0\u5357\u5e02\u00b7\u53f0\u7063", "utc": 1455793054000, "level": 0, "avatar": "http://filestoresg1.beetalkmobile.com:8081/file/2", "name": "User blocked"}, "content": "\u6211\u4ea4\u904e\u7684\u90fd\u662f\u5f1f\u5f1f\uff0c<br />\u4e0d\u7ba1\u54e5\u54e5\u6216\u5f1f\u5f1f\uff0c\u6c38\u9060\u6709\u7684\u4eba\u5c31\u662f\u6210\u719f\uff0c<br />\u6709\u7684\u4eba\u5c31\u662f\u5e7c\u7a1a\uff0c\u5c31\u770b\u4f60\u80fd\u63a5\u53d7\u90a3\u4e00\u7a2e\u500b\u6027\u7684\u4eba\u3002<br />", "urls": [], "replies": {"first": [{"content": "\u59b3\u5011\u5dee\u5e7e\u6b72\u5440\uff1f\u6211\u60f3\u6211\u771f\u7684\u7f3a\u4e4f\u52c7\u6c23", "reply": "", "id": 20516788, "name": "\u5c0f\u51b7"}], "last": [{"content": "\u6709\u5dee2\u6b72\uff0c\u4e5f\u6709\u5dee12\u6b72\u311f", "reply": "", "id": 20533757, "name": "User blocked"}, {"content": "\u5f1f\u5f1f\u90fd\u5f88\u611b\u6211\uff0c", "reply": "", "id": 20533782, "name": "User blocked"}], "noMoreReplies": true}, "images": [], "id": 31939042}]}
