{"noMoreComments": true, "cursorEnd": 0, "id": "3566561", "comments": [{"postBy": {"location": "\u65b0\u5317\u5e02\u00b7\u53f0\u7063", "utc": 1461307392000, "level": 0, "avatar": "http://filestoresg1.beetalkmobile.com:8081/file/4385170131753416922", "name": "goldberg chi"}, "content": "\u4e0d\u8981\u60f3\u592a\u591a<br />\u56e0\u70ba\u73fe\u5728\u7576\u5175\u5df2\u7d93\u7b97\u5f88\u77ed\u4e86<br />\u60f3\u7684\u592a\u591a\u8b93\u81ea\u5df1\u56f0\u64fe\u6182\u5fc3 \u81ea\u4fe1\u90fd\u4e0d\u898b\u4e86<br />\u53cd\u800c\u5c0d\u5169\u500b\u4eba\u7684\u611f\u60c5<br />\u6c92\u6709\u5e6b\u52a9<br />\u56e0\u70ba\u4f60\u6f38\u6f38\u7684\u4e0d\u958b\u5fc3 \u80e1\u601d\u4e82\u60f3<br />\u5bb9\u6613\u8b93\u5c0d\u65b9\u611f\u5230\u75b2\u7d2f (\u4fe1\u4efb\u5f88\u91cd\u8981)<br />\u8a18\u5f97\u958b\u5fc3\u9ede\u4e0d\u9700\u60f3\u592a\u591a<br />\u611f\u60c5\u662f\u4e0d\u662f\u5f97\u7d93\u7684\u8d77\u8003\u9a57<br />\u662f\u5728\u5f7c\u6b64\u5594", "urls": [], "replies": {"first": [{"content": "\u8b1d\u8b1d\u5b78\u9577\u7d66\u4e88\u9f13\u52f5\uff01", "reply": "", "id": 23952546, "name": "\ud83d\udd30Roots\ud83c\uddef\ud83c\uddf5"}], "last": [], "noMoreReplies": true}, "images": [], "id": 37094807}]}
