{"noMoreComments": true, "cursorEnd": 0, "id": "3882943", "comments": [{"postBy": {"location": "", "utc": 1465450520000, "level": 0, "avatar": "http://filestoresg1.beetalkmobile.com:8081/file/-5240503314582094608", "name": "."}, "content": "\u63a8~\u611b\u6253\u93e2\u7684\u90fd\u662f\u6b63\u59b9\u2764", "urls": [], "replies": {"first": [], "last": [], "noMoreReplies": true}, "images": [], "id": 40898913}, {"postBy": {"location": "\u65b0\u5317\u5e02\u00b7\u53f0\u7063", "utc": 1465791746000, "level": 0, "avatar": "http://filestoresg1.beetalkmobile.com:8081/file/4958972275515977175", "name": "\u7246\u89d2\u7684\u8309\u8389"}, "content": "\u6709\u8208\u8da3\uff01\u76ee\u524d\u5728\u5b78", "urls": [], "replies": {"first": [{"content": "\u8981\u52a0\u5165\u4e00\u8d77\u804a\u5929\u55ce\u263a\u263a\u263a", "reply": "", "id": 26807611, "name": "\u2764\ufe0fAnn\u2764\ufe0fMiss\u773c\u888b"}], "last": [], "noMoreReplies": true}, "images": [], "id": 41205500}, {"postBy": {"location": "\u65b0\u5317\u5e02\u00b7\u53f0\u7063", "utc": 1465805261000, "level": 0, "avatar": "http://filestoresg1.beetalkmobile.com:8081/file/-3424168377702340096", "name": "HenryLiang"}, "content": "\u8acb\u554f\u90fd\u5728\u54ea\u6253\u554a \u53ef\u52a0\u55ce \u6211\u65b0\u624b\ud83d\ude02\ud83d\ude02", "urls": [], "replies": {"first": [], "last": [], "noMoreReplies": true}, "images": [], "id": 41220170}, {"postBy": {"location": "\u6843\u5712\u5e02\u00b7\u53f0\u6e7e", "utc": 1465811741000, "level": 0, "avatar": "http://filestoresg1.beetalkmobile.com:8081/file/-7284341498471546110", "name": "\u963f\u5584"}, "content": "\u9cf3\u51f0\u6a5f\u5662 \u65b0\u624b", "urls": [], "replies": {"first": [], "last": [], "noMoreReplies": true}, "images": [], "id": 41226976}, {"postBy": {"location": "\u53f0\u4e2d\u5e02\u00b7\u53f0\u7063", "utc": 1465874612000, "level": 0, "avatar": "http://filestoresg1.beetalkmobile.com:8081/file/-3636115735345444682", "name": "\ud83d\udc3a\u72fc\u5b50\u26e6"}, "content": "++", "urls": [], "replies": {"first": [], "last": [], "noMoreReplies": true}, "images": [], "id": 41283829}, {"postBy": {"location": "", "utc": 1466826756000, "level": 0, "avatar": "http://filestoresg1.beetalkmobile.com:8081/file/7220691872352351488", "name": "Irwin"}, "content": "++\ud83d\ude4f", "urls": [], "replies": {"first": [], "last": [], "noMoreReplies": true}, "images": [], "id": 42167959}, {"postBy": {"location": "\u65b0\u5317\u5e02\u00b7\u53f0\u7063", "utc": 1466859789000, "level": 0, "avatar": "http://filestoresg1.beetalkmobile.com:8081/file/5487094098780657842", "name": "\u7f50\u982d"}, "content": "\u8acb\u554f\u5728\u54ea\u88e1\u6253\u6a19?<br />", "urls": [], "replies": {"first": [], "last": [], "noMoreReplies": true}, "images": [], "id": 42202127}]}
