{"noMoreComments": true, "cursorEnd": 0, "id": "3287328", "comments": [{"postBy": {"location": "\u53f0\u4e2d\u5e02\u00b7\u53f0\u7063", "utc": 1457800192000, "level": 0, "avatar": "http://filestoresg1.beetalkmobile.com:8081/file/-4313707365881584609", "name": "\u8521\u54f2"}, "content": "\u6709\u5927\u5b78\u751f\ud83d\ude02", "urls": [], "replies": {"first": [{"content": "\u52a0 \ud83d\ude02\ud83d\ude02", "reply": "", "id": 21947750, "name": "\u52d5\u614b"}, {"content": "\ud83d\ude02", "reply": "\u52d5\u614b", "id": 21974124, "name": "\u8521\u54f2"}], "last": [], "noMoreReplies": true}, "images": [], "id": 33779298}, {"postBy": {"location": "China", "utc": 1457826666000, "level": 0, "avatar": "http://filestoresg1.beetalkmobile.com:8081/file/4133392964120130733", "name": "\u5e7b\u60f3\u4e16\u754c"}, "content": "\u6211\u500b\u4eba\u662f\u8d0a\u6210\u540c\u6027\u4ea4\u7db2\u7684\uff01", "urls": [], "replies": {"first": [{"content": "\u86e4\ud83d\ude02\u5565\u4ea4\u5f80", "reply": "", "id": 21947739, "name": "\u52d5\u614b"}, {"content": "\u984d\uff0c\u4e0d\u901f\u60f3\u8a8d\u8a66\u5973\u751f\uff1f\u6211\u770b\u932f\u4e86\u55ce\uff1f", "reply": "\u52d5\u614b", "id": 21947930, "name": "\u5e7b\u60f3\u4e16\u754c"}], "last": [], "noMoreReplies": true}, "images": [], "id": 33793908}]}
