{"noMoreComments": true, "cursorEnd": 0, "id": "3118633", "comments": [{"postBy": {"location": "\u65b0\u5317\u5e02\u00b7\u53f0\u7063", "utc": 1455658862000, "level": 0, "avatar": "http://filestoresg1.beetalkmobile.com:8081/file/-5184804250323885427", "name": "\u6708\u8001"}, "content": "Hi \u6211\u662f\u53f0\u6771\u9054\u4ec1\u7684\u963f\u6392 ", "urls": [], "replies": {"first": [], "last": [], "noMoreReplies": true}, "images": [], "id": 31818429}, {"postBy": {"location": "\u9ad8\u96c4\u5e02\u00b7\u53f0\u7063", "utc": 1455666491000, "level": 0, "avatar": "http://filestoresg1.beetalkmobile.com:8081/file/-7225250437962369221", "name": "\u9ec4\u6cb3"}, "content": "\u5341\u5341", "urls": [], "replies": {"first": [], "last": [], "noMoreReplies": true}, "images": [], "id": 31821043}, {"postBy": {"location": "\u65b0\u5317\u5e02\u00b7\u53f0\u7063", "utc": 1455808611000, "level": 0, "avatar": "http://filestoresg1.beetalkmobile.com:8081/file/4165414056004883441", "name": "\u4faf\u723a"}, "content": "\u5f88\u9ad8\u8208\u8a8d\u8b58\u59b3", "urls": [], "replies": {"first": [], "last": [], "noMoreReplies": true}, "images": [], "id": 31960219}, {"postBy": {"location": "\u53f0\u6771\u7e23\u00b7\u53f0\u7063", "utc": 1460953506000, "level": 0, "avatar": "http://filestoresg1.beetalkmobile.com:8081/file/-1435500373803416468", "name": "\u518d\u898b"}, "content": "\u54c8\u56c9", "urls": [], "replies": {"first": [], "last": [], "noMoreReplies": true}, "images": [], "id": 36745726}, {"postBy": {"location": "\u9ad8\u96c4\u5e02\u00b7\u53f0\u7063", "utc": 1460968672000, "level": 0, "avatar": "http://filestoresg1.beetalkmobile.com:8081/file/6139953308301628160", "name": "J"}, "content": "\u5f88\u9177\u8036\u4f60 \u52a0", "urls": [], "replies": {"first": [], "last": [], "noMoreReplies": true}, "images": [], "id": 36761778}, {"postBy": {"location": "\u53f0\u5317\u5e02\u00b7\u53f0\u7063", "utc": 1460969306000, "level": 0, "avatar": "http://filestoresg1.beetalkmobile.com:8081/file/1979090150915390976", "name": "A"}, "content": "\u597d\u6027\u611f\u7684\u5634\u5507\uff0c\u591a\u611b\u81ea\u5df1\u4e00\u9ede", "urls": [], "replies": {"first": [], "last": [], "noMoreReplies": true}, "images": [], "id": 36762516}]}
