{"noMoreComments": true, "cursorEnd": 0, "id": "3787365", "comments": [{"postBy": {"location": "\u53f0\u5317\u5e02\u00b7\u53f0\u7063", "utc": 1464156180000, "level": 0, "avatar": "http://filestoresg1.beetalkmobile.com:8081/file/-3061524141565463135", "name": "\u8863"}, "content": "\u6709\u50cf\u6df7\u7684\uff0c\u505a\u500b\u57fa\u56e0\u6aa2\u6e2c\u5c31\u77e5\u9053\u6709\u7121\u6df7\u8840", "urls": [], "replies": {"first": [{"content": "\u505a\u4e00\u6b21\u6aa2\u9a57\u4e0d\u4fbf\u5b9c\u5462", "reply": "", "id": 25774858, "name": "Jen"}], "last": [], "noMoreReplies": true}, "images": [], "id": 39763153}]}
