{"noMoreComments": true, "cursorEnd": 0, "id": "3347567", "comments": [{"postBy": {"location": "\u53f0\u4e2d\u5e02\u00b7\u53f0\u7063", "utc": 1458874317000, "level": 0, "avatar": "http://filestoresg1.beetalkmobile.com:8081/file/-9194591212763312866", "name": "Joe"}, "content": "\u50f9\u4f4d\u5462\uff1f", "urls": [], "replies": {"first": [{"content": "\u5df2\u79c1", "reply": "", "id": 22429146, "name": "Mengzhen"}], "last": [], "noMoreReplies": true}, "images": [], "id": 34800391}, {"postBy": {"location": "\u53f0\u4e2d\u5e02\u00b7\u53f0\u7063", "utc": 1458882546000, "level": 0, "avatar": "http://filestoresg1.beetalkmobile.com:8081/file/-8370989938118979065", "name": "\u963f\u5091"}, "content": "\u591a\u5c11\u5462", "urls": [], "replies": {"first": [{"content": "\u5df2\u79c1", "reply": "", "id": 22429668, "name": "Mengzhen"}], "last": [], "noMoreReplies": true}, "images": [], "id": 34808924}, {"postBy": {"location": "\u82d7\u6817\u7e23\u00b7\u53f0\u7063", "utc": 1458882953000, "level": 0, "avatar": "http://filestoresg1.beetalkmobile.com:8081/file/-7127727062111070024", "name": "\u7c89\u59b9\ud83c\udf42"}, "content": "\u6211\u60f3\u554f\u50f9\u4f4d", "urls": [], "replies": {"first": [{"content": "\u5df2\u79c1", "reply": "", "id": 22430121, "name": "Mengzhen"}], "last": [], "noMoreReplies": true}, "images": [], "id": 34809405}]}
