{"noMoreComments": true, "cursorEnd": 0, "id": "3673141", "comments": [{"postBy": {"location": "\u53f0\u5317\u5e02\u00b7\u53f0\u7063", "utc": 1462677541000, "level": 0, "avatar": "http://filestoresg1.beetalkmobile.com:8081/file/-7820377589758724793", "name": "\u5d50"}, "content": "\u53f0\u4e2d+1", "urls": [], "replies": {"first": [{"content": "\u55e8e :)", "reply": "", "id": 24851245, "name": "\u7693\u5947"}], "last": [], "noMoreReplies": true}, "images": [], "id": 38412760}, {"postBy": {"location": "\u53f0\u5357\u5e02\u00b7\u53f0\u7063", "utc": 1462679172000, "level": 0, "avatar": "http://filestoresg1.beetalkmobile.com:8081/file/-2756524023933568274", "name": "Nemo\u3161"}, "content": "+5", "urls": [], "replies": {"first": [{"content": "\u660e\u660e\u5c31+2\n\u90a3\u4f86\u7684+5\n\u54c8\u54c8\u54c8", "reply": "", "id": 24851207, "name": "\u7693\u5947"}], "last": [{"content": "\u611b\u4f60\u5537", "reply": "Nemo\u3161", "id": 25385729, "name": "\u7693\u5947"}, {"content": "\ud83d\ude18\ud83d\ude18", "reply": "\u7693\u5947", "id": 25421154, "name": "Nemo\u3161"}], "noMoreReplies": false}, "images": [], "id": 38414653}, {"postBy": {"location": "\u65b0\u5317\u5e02\u00b7\u53f0\u7063", "utc": 1462679304000, "level": 0, "avatar": "http://filestoresg1.beetalkmobile.com:8081/file/-96081922223175618", "name": "\u5f37\u984f\u6b61\u7b11"}, "content": "+3", "urls": [], "replies": {"first": [{"content": "\u55e8e :)\n\u6628\u5929\u624d\u53bb\u81fa\u5317 \u54c8\u54c8", "reply": "", "id": 24851325, "name": "\u7693\u5947"}], "last": [{"content": "\u4e5f\u662f\u53ef\u4ee5\u5566\uff01\uff01\uff01", "reply": "", "id": 24926107, "name": "\u5f37\u984f\u6b61\u7b11"}, {"content": "\u597d\u5537", "reply": "\u5f37\u984f\u6b61\u7b11", "id": 25385724, "name": "\u7693\u5947"}], "noMoreReplies": false}, "images": [], "id": 38414797}, {"postBy": {"location": "\u53f0\u4e2d\u5e02\u00b7\u53f0\u7063", "utc": 1462680167000, "level": 0, "avatar": "http://filestoresg1.beetalkmobile.com:8081/file/-7298926504720583636", "name": "Mars"}, "content": "+1", "urls": [], "replies": {"first": [{"content": "\u54e5\u54e5,\u6211\u77e5\u9053\u5537 \n\u5982\u679c\u6211\u4e0d\u77e5\u9053\n\u6211\u53ef\u80fd\u6703\u88ab\u5abd\u5abd\u6253\u6253 \u54c8\u54c8", "reply": "", "id": 24851358, "name": "\u7693\u5947"}], "last": [{"content": "\u563f\u563f", "reply": "Mars", "id": 25385721, "name": "\u7693\u5947"}, {"content": "\u563f\u563f\u4ec0\u9ebc\ud83d\ude02", "reply": "\u7693\u5947", "id": 25387846, "name": "Mars"}], "noMoreReplies": false}, "images": [], "id": 38415702}, {"postBy": {"location": "\u96f2\u6797\u7e23\u00b7\u53f0\u7063", "utc": 1462682402000, "level": 0, "avatar": "http://filestoresg1.beetalkmobile.com:8081/file/8350691864169923073", "name": "170\ud83d\udc8b"}, "content": "\u5609\u7fa9+4\ud83d\ude02", "urls": [], "replies": {"first": [{"content": "\u4e0a\u9762\u6c92\u6709\u90fd\u4e82\u4e82\u52a0,\u771f\u662f\u7684", "reply": "", "id": 24851298, "name": "\u7693\u5947"}], "last": [{"content": "\u6211\u6015\u4f60\u5fd8\u8a18\u6211\u54ea\u88e1\u4eba\u54c8\u54c8\u54c8", "reply": "\u7693\u5947", "id": 24858710, "name": "170\ud83d\udc8b"}, {"content": "\u4e0d\u53ef\u80fd\u5fd8\u8a18\u7684", "reply": "170\ud83d\udc8b", "id": 24864276, "name": "\u7693\u5947"}], "noMoreReplies": true}, "images": [], "id": 38418032}, {"postBy": {"location": "\u5609\u7fa9\u7e23\u00b7\u53f0\u7063", "utc": 1462682656000, "level": 0, "avatar": "http://filestoresg1.beetalkmobile.com:8081/file/-6959009193410522613", "name": "\u09e1\u09e2 \u09e2\u0361\u035c\u5c0f\u2606\u09e1\u09e2 \u0361\u035c\u8ed2\u2606\u09e1"}, "content": "\u53f0\u4e2d+1", "urls": [], "replies": {"first": [{"content": "\u55e8e\n\u81fa\u4e2d\u54ea\u88e1?", "reply": "", "id": 24851501, "name": "\u7693\u5947"}], "last": [{"content": "\u5357\u5340 \u6709\u4ec0\u9ebc??", "reply": "\u09e1\u09e2 \u09e2\u0361\u035c\u5c0f\u2606\u09e1\u09e2 \u0361\u035c\u8ed2\u2606\u09e1", "id": 25385708, "name": "\u7693\u5947"}, {"content": "\u4e2d\u8208\u5927\u5b78", "reply": "", "id": 25397146, "name": "\u09e1\u09e2 \u09e2\u0361\u035c\u5c0f\u2606\u09e1\u09e2 \u0361\u035c\u8ed2\u2606\u09e1"}], "noMoreReplies": false}, "images": [], "id": 38418298}, {"postBy": {"location": "", "utc": 1462684911000, "level": 0, "avatar": "http://filestoresg1.beetalkmobile.com:8081/file/8069765537965364993", "name": "\u6b50\u8463"}, "content": "\u53f0\u4e2d\u897f\u5c6f^_^", "urls": [], "replies": {"first": [{"content": "\u96e2\u6211\u597d\u9060\u5537\n\u89ba\u5f97\u96e3\u904e\u02ca\u02cb", "reply": "", "id": 24851430, "name": "\u7693\u5947"}], "last": [], "noMoreReplies": true}, "images": [], "id": 38420714}, {"postBy": {"location": "\u53f0\u5317\u5e02\u00b7\u53f0\u7063", "utc": 1462686622000, "level": 0, "avatar": "http://filestoresg1.beetalkmobile.com:8081/file/-6301264837522863663", "name": "\ud83d\udc7b\ud83d\udc7b"}, "content": "\u53f0\u4e2d+1", "urls": [], "replies": {"first": [{"content": "\u55e8e", "reply": "", "id": 24851490, "name": "\u7693\u5947"}], "last": [{"content": "\u8ddd\u96e2", "reply": "\u7693\u5947", "id": 24926944, "name": "\ud83d\udc7b\ud83d\udc7b"}, {"content": "\u8d85\u7d1a \u54c8\u54c8", "reply": "", "id": 25385697, "name": "\u7693\u5947"}], "noMoreReplies": false}, "images": [], "id": 38422611}, {"postBy": {"location": "\u53f0\u5357\u5e02\u00b7\u53f0\u7063", "utc": 1462688696000, "level": 0, "avatar": "http://filestoresg1.beetalkmobile.com:8081/file/7805385784274729001", "name": "\u5c0f\u7070\u96c4"}, "content": "+2", "urls": [], "replies": {"first": [{"content": "\u55e8e", "reply": "", "id": 24851492, "name": "\u7693\u5947"}], "last": [], "noMoreReplies": true}, "images": [], "id": 38424884}, {"postBy": {"location": "", "utc": 1462691513000, "level": 0, "avatar": "http://filestoresg1.beetalkmobile.com:8081/file/-7583110693713066369", "name": "\u5c08\u5c6c"}, "content": "\u9ad8\u96c4", "urls": [], "replies": {"first": [{"content": "\u9ad8\u96c4,\u597d\u9060\u02ca\u02cb\n\u80fd\u4e0d\u80fd\u8fd1\u4e00\u9ede\u02ca\u02cb", "reply": "", "id": 24851465, "name": "\u7693\u5947"}], "last": [{"content": "\u54c8\u54c8\ud83d\ude04\ud83d\ude04\ud83d\ude04", "reply": "\u7693\u5947", "id": 24851787, "name": "\u5c08\u5c6c"}, {"content": "\u7b11\u4ec0\u9ebc :)", "reply": "", "id": 24898282, "name": "\u7693\u5947"}], "noMoreReplies": false}, "images": [], "id": 38427705}, {"postBy": {"location": "\u6843\u5712\u5e02\u00b7\u53f0\u7063", "utc": 1462692672000, "level": 0, "avatar": "http://filestoresg1.beetalkmobile.com:8081/file/-4260221626470128896", "name": "mei"}, "content": "\u5f70\u5316", "urls": [], "replies": {"first": [{"content": "\u5f70\u5316\u9019\u500b\u96e2\u81fa\u4e2d\u8fd1 \u54c8\u54c8", "reply": "", "id": 24851993, "name": "\u7693\u5947"}], "last": [{"content": "\u54c8\u54c8", "reply": "", "id": 24852032, "name": "mei"}, {"content": "\u563b\u563b", "reply": "", "id": 24852837, "name": "\u7693\u5947"}], "noMoreReplies": true}, "images": [], "id": 38428985}]}
