{"noMoreComments": false, "cursorEnd": 24, "id": "3700065", "comments": [{"postBy": {"location": "\u53f0\u4e2d\u5e02\u00b7\u53f0\u7063", "utc": 1462992057000, "level": 0, "avatar": "http://filestoresg1.beetalkmobile.com:8081/file/-7682886976213083248", "name": "\u731c\u4e0d\u900f"}, "content": "\u771f\u7684\u55ce\uff1f\u771f\u4eba\u90b1\u6bd4\u7279\u6211\u9700\u8981\u59b3\u7684\u52a0\u6301,\u55ae\u8eab7\u500b\u6708\u4e86\ud83d\ude02\ud83d\ude02\ud83d\ude02", "urls": [], "replies": {"first": [{"content": "\u624d\u55ae\u8eab\u4e03\u500b\u6708  \u6211\u55ae\u8eab\u4e5d\u5e74\u4e86\u5730\u5716\u90fd\u756b\u5168\u4e16\u754c\u4e86  \u54c8\u54c8\u54c8\u54c8\u2026", "reply": "", "id": 25677479, "name": "\u9245\u5049"}], "last": [{"content": "\u6211\u4ee5\u70ba\u621115\u5e74\u5df2\u7d93\u9802\u4e86\u3002\u3002", "reply": "", "id": 34287031, "name": "\u83ca\u5730\u5584\u4eba"}, {"content": "\u621132\u5e74\u600e\u9ebc\u8fa6", "reply": "\u83ca\u5730\u5584\u4eba", "id": 38661369, "name": "\u5c0f\u5929\u624d"}], "noMoreReplies": false}, "images": [], "id": 38729936}, {"postBy": {"location": "\u96f2\u6797\u7e23\u00b7\u53f0\u7063", "utc": 1462992193000, "level": 0, "avatar": "http://filestoresg1.beetalkmobile.com:8081/file/-8862205538891866805", "name": "ming"}, "content": "\u501f\u6211\u4e00\u96bb\u7bad\u5427", "urls": [], "replies": {"first": [], "last": [], "noMoreReplies": true}, "images": [], "id": 38730017}, {"postBy": {"location": "\u65b0\u5317\u5e02\u00b7\u53f0\u7063", "utc": 1463024122000, "level": 0, "avatar": "http://filestoresg1.beetalkmobile.com:8081/file/-8406304046809448318", "name": "\u60e1\u9b54\u8f49\u751f"}, "content": "\u8ddf\u59b3\u804a\u5929\u4e00\u4e0b\u5594\uff0c\u90b1\u6bd4\u7279\u5c0f\u59d0\u3002", "urls": [], "replies": {"first": [], "last": [], "noMoreReplies": true}, "images": [], "id": 38748428}, {"postBy": {"location": "", "utc": 1463028004000, "level": 0, "avatar": "http://filestoresg1.beetalkmobile.com:8081/file/-6610981885676706304", "name": "nino"}, "content": "\u90a3\u6211\u4e5f\u60f3\u88ab\u59b3\u7684\u7bad\u5c04\u4e2d", "urls": [], "replies": {"first": [], "last": [], "noMoreReplies": true}, "images": [], "id": 38752589}, {"postBy": {"location": "\u53f0\u5317\u5e02\u00b7\u53f0\u7063", "utc": 1463034149000, "level": 0, "avatar": "http://filestoresg1.beetalkmobile.com:8081/file/5558103864128328124", "name": "Oneill"}, "content": "\u65e2\u7136\u8ddf\u59b3\u804a\u5929\u7684\u7537\u751f\uff0c\u5230\u6700\u5f8c\u90fd\u6c92\u5728\u4e00\u8d77\uff0c\u8868\u793a\u7537\u751f\u4e0d\u5920\u559c\u6b61\u59b3\uff0c\u4e0d\u5920\u559c\u6b61\u59b3\u7684\u7537\u751f\uff0c\u65e9\u65e9\u7d50\u675f\u4e5f\u597d\uff0c\u591a\u89c0\u5bdf\uff0c\u4e00\u5b9a\u53ef\u4ee5\u627e\u5230\u5c6c\u65bc\u59b3\u7684 Mr. right\u3002", "urls": [], "replies": {"first": [], "last": [], "noMoreReplies": true}, "images": [], "id": 38759405}, {"postBy": {"location": "\u53f0\u4e2d\u5e02\u00b7\u53f0\u7063", "utc": 1463038708000, "level": 0, "avatar": "http://filestoresg1.beetalkmobile.com:8081/file/7726292398730548480", "name": "brook"}, "content": "\u8f9b\u82e6\u4f60\u4e86", "urls": [], "replies": {"first": [], "last": [], "noMoreReplies": true}, "images": [], "id": 38763929}, {"postBy": {"location": "\u53f0\u5317\u5e02\u00b7\u53f0\u7063", "utc": 1463086827000, "level": 0, "avatar": "http://filestoresg1.beetalkmobile.com:8081/file/-1231512392617550466", "name": "\u99ac\u514b\u767d"}, "content": "\u5012\u6578\u7b2c\u4e8c\u500b\u5973\u670b\u53cb", "urls": [], "replies": {"first": [], "last": [], "noMoreReplies": true}, "images": [], "id": 38814611}, {"postBy": {"location": "\u53f0\u5317\u5e02\u00b7\u53f0\u7063", "utc": 1463088683000, "level": 0, "avatar": "http://filestoresg1.beetalkmobile.com:8081/file/-5370016972803935653", "name": "\u963f\u6fa4\u897f"}, "content": "\u8dea\u6c42\u5c04\u6211\uff01\uff01\uff01\uff01", "urls": [], "replies": {"first": [], "last": [], "noMoreReplies": true}, "images": [], "id": 38815123}, {"postBy": {"location": "\u53f0\u5357\u5e02\u00b7\u53f0\u7063", "utc": 1463089877000, "level": 0, "avatar": "http://filestoresg1.beetalkmobile.com:8081/file/-517376279327198245", "name": "\u7fbd\u5fd7\u7965"}, "content": "\u6211\u4e5f\u89ba\u5f97\u6211\u662f\u5012\u6578\u7b2c\u4e8c\u500b\u7537\u670b\u53cb\uff0c\u8ddf\u6211\u806f\u8abc\u904e\u6216\u51fa\u904a\u904e\u7684\u5973\u5b69\u5b50\uff0c\u90fd\u5f88\u5feb\u627e\u5230\u7537\u670b\u53cb", "urls": [], "replies": {"first": [], "last": [], "noMoreReplies": true}, "images": [], "id": 38815422}, {"postBy": {"location": "\u53f0\u5357\u5e02\u00b7\u53f0\u7063", "utc": 1463103709000, "level": 0, "avatar": "http://filestoresg1.beetalkmobile.com:8081/file/-6558973884795948031", "name": "\ud83d\ude2c\ud83d\ude2c\ud83d\ude2c"}, "content": "\u771f\u7684\u55ce\u3002\u6211\u9700\u8981\u59b3\u7684\u7bad", "urls": [], "replies": {"first": [], "last": [], "noMoreReplies": true}, "images": [], "id": 38823171}, {"postBy": {"location": "\u53f0\u4e2d\u5e02\u00b7\u53f0\u7063", "utc": 1463105451000, "level": 0, "avatar": "http://filestoresg1.beetalkmobile.com:8081/file/-438810674644170232", "name": "\u9f8d"}, "content": "\u501f\u6211\u5e7e\u628a\u5f13\u7bad\u5427\uff01<br />\u6211\u5f88\u9700\u8981QAQ", "urls": [], "replies": {"first": [], "last": [], "noMoreReplies": true}, "images": [], "id": 38824609}, {"postBy": {"location": "\u53f0\u5357\u5e02\u00b7\u53f0\u7063", "utc": 1463125491000, "level": 0, "avatar": "http://filestoresg1.beetalkmobile.com:8081/file/-6816370658424010602", "name": "\u963f\u52f3"}, "content": "\u9019\u6a23\u4e0d\u932f\u6b38\uff0c\u59b3\u662f\u7537\u751f\u6211\u662f\u5973\u751f\uff0c\u8ddf\u559c\u6b61\u7684\u5973\u751f\u804a\u5929\u5f8c\u5c0d\u65b9\u5c31\u627e\u5230\u597d\u5c0d\u8c61\u4e86", "urls": [], "replies": {"first": [], "last": [], "noMoreReplies": true}, "images": [], "id": 38844809}, {"postBy": {"location": "\u53f0\u4e2d\u5e02\u00b7\u53f0\u7063", "utc": 1463128661000, "level": 0, "avatar": "http://filestoresg1.beetalkmobile.com:8081/file/-1445625785319579136", "name": "\u9322\u4f86\u4e5f"}, "content": "\u662f\u5440\uff0c\u600e\u9ebc\u4e0d\u7ba1\u600e\u9ebc\u52aa\u529b\uff0c\u5230\u6700\u5f8c\u90fd\u6210\u4e86\u54e5\u54e5\u3001\u5de5\u5177\u4eba\uff0c\u597d\u7d2f\u597d\u7d2f\u7684\u5440", "urls": [], "replies": {"first": [], "last": [], "noMoreReplies": true}, "images": [], "id": 38848067}, {"postBy": {"location": "\u5c4f\u6771\u7e23\u00b7\u53f0\u7063", "utc": 1463130764000, "level": 0, "avatar": "http://filestoresg1.beetalkmobile.com:8081/file/7917512878027085336", "name": "HmiCat"}, "content": "\u8acb\u60a8\u4e5f\u628a\u60a8\u624b\u4e0a\u7684\u5f13\u7bad\u5c04\u5411\u6211", "urls": [], "replies": {"first": [], "last": [], "noMoreReplies": true}, "images": [], "id": 38850228}, {"postBy": {"location": "\u65b0\u5317\u5e02\u00b7\u53f0\u7063", "utc": 1463132231000, "level": 0, "avatar": "http://filestoresg1.beetalkmobile.com:8081/file/-2746586630092294359", "name": "\u958b\u8eca\u649e\u5230\u59b3\u2122"}, "content": "\u52a0\u6cb9\u4f60\u53ef\u4ee5\u7684(^_-)", "urls": [], "replies": {"first": [], "last": [], "noMoreReplies": true}, "images": [], "id": 38851775}, {"postBy": {"location": "\u82d7\u6817\u7e23\u00b7\u53f0\u7063", "utc": 1463144000000, "level": 0, "avatar": "http://filestoresg1.beetalkmobile.com:8081/file/7744492631301572479", "name": "Liang"}, "content": "\u9019\u6a23\u4e5f\u4e0d\u932f\u554a<br />\u6551\u4eba\u4e00\u547d\u52dd\u9020\u4e03\u6975\u6d6e\u5c60<br />\u662f\u9019\u6a23\u8aaa\u7684\uff1f\u89ba\u5f97\u602a\u602a\u7684\u2026\u2026", "urls": [], "replies": {"first": [], "last": [], "noMoreReplies": true}, "images": [], "id": 38864387}, {"postBy": {"location": "\u65b0\u7af9\u5e02\u00b7\u53f0\u7063", "utc": 1463150295000, "level": 0, "avatar": "http://filestoresg1.beetalkmobile.com:8081/file/-8090404468215894525", "name": "\u711c"}, "content": "\u4f60\u597d\u554a", "urls": [], "replies": {"first": [], "last": [], "noMoreReplies": true}, "images": [], "id": 38873281}, {"postBy": {"location": "Taichung City\u00b7Taiwan", "utc": 1463291879000, "level": 0, "avatar": "http://filestoresg1.beetalkmobile.com:8081/file/-6573716135832229567", "name": "\u9945\u982d\u963f\u91ac"}, "content": "\u9700\u8981\u52a0\u6301\u554a~", "urls": [], "replies": {"first": [], "last": [], "noMoreReplies": true}, "images": [], "id": 38998307}, {"postBy": {"location": "\u82b1\u84ee\u7e23\u00b7\u53f0\u7063", "utc": 1463296466000, "level": 0, "avatar": "http://filestoresg1.beetalkmobile.com:8081/file/6748636357851312645", "name": "\u9ed1\u718a"}, "content": "\u4e0d\u6703\u554a\uff01\u59b3\u5f88\u751c\u7f8e\u554a\uff01<br />\u90a3\u53ef\u4ee5\u52a0\u59b3\u597d\u53cb\u804a\u804a\u5929\u55ce\uff1f", "urls": [], "replies": {"first": [], "last": [], "noMoreReplies": true}, "images": [], "id": 39003319}]}
