{"noMoreComments": true, "cursorEnd": 0, "id": "3700982", "comments": [{"postBy": {"location": "\u9ad8\u96c4\u5e02\u00b7\u53f0\u7063", "utc": 1463015703000, "level": 0, "avatar": "http://filestoresg1.beetalkmobile.com:8081/file/8770288593290011490", "name": "\u91d1\u51f1\u745e"}, "content": "\u597d \u2026 \u8aaa\u7684\u771f\u597d\u3002\u4e0d\u5f97\u4e0d\u7d66\u59b3\ud83d\udc4d", "urls": [], "replies": {"first": [{"content": "\u54c8\u54c8\u3002\u4e00\u76f4\u90fd\u6709\u9019\u7a2e\u611f\u89ba\u3002\u518d\u4e0d\u8aaa\u51fa\u4f86\u6211\u6703\u60b6\u6b7b", "reply": "", "id": 25071661, "name": "\ud83c\udf38"}], "last": [{"content": "\u4e0d\u932f\u554a\uff01\u5176\u5be6\u5f88\u591a\u4eba\u60f3\u8aaa\u5427\u2026  \u7562\u7adf\u662f\u7528\u5fc3\u800c\u4e0d\u662f\u7528\u8089\u9ad4\u5728\u4ea4\u53cb\u7684\u3002", "reply": "\ud83c\udf38", "id": 25071876, "name": "\u91d1\u51f1\u745e"}, {"content": "\u54c8\u54c8 \u4e0d\u662f\u5f88\u591a\u4eba\u90fd\u9019\u6a23\u60f3 \u9019\u88e1\u90e8\u5206\u7684\u4eba\u4e0d\u904e\u90fd\u662f\u70ba\u4e86\u5229\u76ca\u800c\u73a9\u7684", "reply": "\u91d1\u51f1\u745e", "id": 25073893, "name": "\ud83c\udf38"}], "noMoreReplies": true}, "images": [], "id": 38740697}, {"postBy": {"location": "", "utc": 1463037057000, "level": 0, "avatar": "http://filestoresg1.beetalkmobile.com:8081/file/6166509823081323042", "name": "\u6211\u8089\u591a\u54ac\u6211\u963f"}, "content": "\u8b9a\u8fa3<br />\u8aaa\u7684\u597d<br />", "urls": [], "replies": {"first": [], "last": [], "noMoreReplies": true}, "images": [], "id": 38762397}, {"postBy": {"location": "\u82d7\u6817\u7e23\u00b7\u53f0\u7063", "utc": 1463039656000, "level": 0, "avatar": "http://filestoresg1.beetalkmobile.com:8081/file/4269831364397098023", "name": "\u3002"}, "content": "\u59b3\u6fc0\u52d5\u60f9", "urls": [], "replies": {"first": [], "last": [], "noMoreReplies": true}, "images": [], "id": 38764811}, {"postBy": {"location": "\u9ad8\u96c4\u5e02\u00b7\u53f0\u7063", "utc": 1467605545000, "level": 0, "avatar": "http://filestoresg1.beetalkmobile.com:8081/file/1463552239371838736", "name": "\u7d05\u6bdb"}, "content": "\u8aaa\u7684\u771f\u597d<br />\u7d66\u59b3\u4e00\u500b\u8b9a", "urls": [], "replies": {"first": [{"content": "\u54c8\u54c8 \u7d14\u7cb9\u500b\u4eba\u611f\u89ba\u5566", "reply": "", "id": 27993029, "name": "\ud83c\udf38"}], "last": [], "noMoreReplies": true}, "images": [], "id": 42875215}, {"postBy": {"location": "\u53f0\u5357\u5e02\u00b7\u53f0\u7063", "utc": 1467608822000, "level": 0, "avatar": "http://filestoresg1.beetalkmobile.com:8081/file/2235220296624654592", "name": "kevingun"}, "content": "\u9019\u5c31\u662f\u4eba\u751f", "urls": [], "replies": {"first": [], "last": [], "noMoreReplies": true}, "images": [], "id": 42878436}, {"postBy": {"location": "\u65b0\u5317\u5e02\u00b7\u53f0\u7063", "utc": 1467627805000, "level": 0, "avatar": "http://filestoresg1.beetalkmobile.com:8081/file/-7613639729174592134", "name": "\u571f\u57ce\u5927\u611b"}, "content": "\u6c92\u8fa6\u6cd5\u9019\u88e1\u7684\u74b0\u5883\u5c31\u662f\u9019\u6a23\uff0c\u60f3\u885d\u4eba\u6c23\u5c31\u5c11\u62b1\u6028\u591a\u812b\u5e7e\u4ef6\uff0c\u5c0d\u59b3\u6bd4\u8f03\u6709\u5e6b\u52a9", "urls": [], "replies": {"first": [{"content": "\u54c8\u54c8 \u8b1b\u9019\u6a23\n\u6211\u4e0d\u7528\u812b\u8863\u5728\u9019\u88e1\u5c31\u5f88\u6709\u4eba\u6c23\u4e86\ud83d\ude01\u6211\u9760\u7684\u662f\u500b\u6027 \u5f88\u62b1\u6b49\u5537", "reply": "", "id": 28007323, "name": "\ud83c\udf38"}], "last": [{"content": "\u54c8 \u770b\u770b\u6b63\u59b9\u5378\u599d\u5f8c\u80fd\u4e0d\u80fd\u770b\u554a\n\u641e\u7b11", "reply": "\u571f\u57ce\u5927\u611b", "id": 28022121, "name": "\ud83c\udf38"}, {"content": "\u871c\u8702\u7684\u6b63\u59b9\u90fd\u662f\u9760\u756b\u599d\uff0c\u4e0d\u7136\u5c31\u662f\u8001\u59b9", "reply": "\ud83c\udf38", "id": 28023510, "name": "\u571f\u57ce\u5927\u611b"}], "noMoreReplies": false}, "images": [], "id": 42896006}]}
