{"noMoreComments": true, "cursorEnd": 0, "id": "3510379", "comments": [{"postBy": {"location": "\u5609\u7fa9\u7e23\u00b7\u53f0\u7063", "utc": 1460600155000, "level": 0, "avatar": "http://filestoresg1.beetalkmobile.com:8081/file/3954613489025471754", "name": "\u6211\u559c\u6b61\u9ed1\u591c"}, "content": "\u6211\u8d85\u559c\u6b61\uff0c\u4f46\u2026\u2026\u73a9\u7684\u8d85\u721b<br />id :\u82b1\u6708\u59ec", "urls": [], "replies": {"first": [{"content": "\u52a0\u6211\u554a", "reply": "", "id": 23506267, "name": "\u4f60\u5a18"}, {"content": "\u6211\u767d\u5929\u5728\u5b78\u6821\uff0c\u665a\u4e0a\u52a0", "reply": "", "id": 23516876, "name": "\u6211\u559c\u6b61\u9ed1\u591c"}], "last": [], "noMoreReplies": true}, "images": [], "id": 36432450}, {"postBy": {"location": "\u9ad8\u96c4\u5e02\u00b7\u53f0\u7063", "utc": 1460610254000, "level": 0, "avatar": "http://filestoresg1.beetalkmobile.com:8081/file/2986539663687360779", "name": "\u7279\u7279"}, "content": "\u4eba\u5bb6\u4e0d\u60f3\u8981...", "urls": [], "replies": {"first": [{"content": "\u7279\u7279\u6b38\u3002\u88ab\u4f60\u6293\u5305", "reply": "", "id": 23506257, "name": "\u4f60\u5a18"}, {"content": "\u5ae9\u5ae9", "reply": "", "id": 23512688, "name": "\u7279\u7279"}], "last": [], "noMoreReplies": true}, "images": ["http://filestoresg1.beetalkmobile.com:8081/file/a53443e40af7e94bc12280d222de677a"], "id": 36441702}]}
