{"noMoreComments": true, "cursorEnd": 0, "id": "3418997", "comments": [{"postBy": {"location": "\u53f0\u5317\u5e02\u00b7\u53f0\u7063", "utc": 1459435792000, "level": 0, "avatar": "http://filestoresg1.beetalkmobile.com:8081/file/1550167376380577348", "name": "\u95dc\u9589"}, "content": "\u52d5\u52d5\u5c0f\u624b \u5e6b\u6211\u6309\u500b\u8b9a&\u52a0\u597d\u53cb\ud83d\ude09", "urls": [], "replies": {"first": [], "last": [], "noMoreReplies": true}, "images": [], "id": 35343213}, {"postBy": {"location": "\u65b0\u7af9\u7e23\u00b7\u53f0\u7063", "utc": 1459441278000, "level": 0, "avatar": "http://filestoresg1.beetalkmobile.com:8081/file/3337266292423326426", "name": "\u8c6a\u5947\u7436"}, "content": "\u9019\u662f\u4f60\u5537", "urls": [], "replies": {"first": [{"content": "\u662f\u5466", "reply": "", "id": 22794065, "name": "\u95dc\u9589"}], "last": [], "noMoreReplies": true}, "images": [], "id": 35351405}, {"postBy": {"location": "\u65b0\u5317\u5e02\u00b7\u53f0\u7063", "utc": 1459458154000, "level": 0, "avatar": "http://filestoresg1.beetalkmobile.com:8081/file/5699906763607456106", "name": ".\u5bd2\u98a8"}, "content": "\u9019\u5c31\u662f\u611b\uff5e", "urls": [], "replies": {"first": [], "last": [], "noMoreReplies": true}, "images": [], "id": 35363268}, {"postBy": {"location": "\u53f0\u4e2d\u5e02\u00b7\u53f0\u7063", "utc": 1459458293000, "level": 0, "avatar": "http://filestoresg1.beetalkmobile.com:8081/file/-3316996766850393491", "name": "\u5927\u7dad"}, "content": "good!", "urls": [], "replies": {"first": [], "last": [], "noMoreReplies": true}, "images": [], "id": 35363310}]}
