{"noMoreComments": true, "cursorEnd": 0, "id": "3709277", "comments": [{"postBy": {"location": "", "utc": 1463128321000, "level": 0, "avatar": "http://filestoresg1.beetalkmobile.com:8081/file/-4334186869498611949", "name": "\ud83d\udc9cTiffany\ud83c\udf80\u5a77"}, "content": "\u9ad8\u4e00\u5546\u7d93\u5594", "urls": [], "replies": {"first": [], "last": [], "noMoreReplies": true}, "images": [], "id": 38847705}, {"postBy": {"location": "\u6843\u5712\u5e02\u00b7\u53f0\u7063", "utc": 1463240716000, "level": 0, "avatar": "http://filestoresg1.beetalkmobile.com:8081/file/-8275709556652504092", "name": "\u534a"}, "content": "\u7b2c\u4e00\u500b\u52fe\u662f\u5df2\u9001\u9054<br />\u7b2c\u4e8c\u500b\u52fe\u662f\u5c0d\u65b9\u5728\u7dda", "urls": [], "replies": {"first": [{"content": "\u5982\u679c\u5df2\u8b80\u5462", "reply": "", "id": 25225282, "name": "\u6dbc"}], "last": [{"content": "\u5594\u5594@@\u8b1d\u8b1d", "reply": "\u534a", "id": 25335460, "name": "\u6dbc"}, {"content": "\u54c8\u54c8\u611f\u8b1d\u60a8\u5c08\u696d\u56de\u7b54\uff0c\u539f\u4f86\u6c92\u6709\u5df2\u8b80\uff0c\u539f\u4f86\u52fe\u662f\u5728\u7dda", "reply": "", "id": 25792953, "name": "\u4fca"}], "noMoreReplies": false}, "images": [], "id": 38958104}]}
