{"noMoreComments": true, "cursorEnd": 0, "id": "3747276", "comments": [{"postBy": {"location": "\u65b0\u5317\u5e02\u00b7\u53f0\u7063", "utc": 1463611586000, "level": 0, "avatar": "http://filestoresg1.beetalkmobile.com:8081/file/-8451454392750902784", "name": "\u5927\u61a8"}, "content": "\u4e56\u4e56 \u9019\u500b\u62ff\u53bb\u73a9\u5427", "urls": [], "replies": {"first": [{"content": "\uff08\u8ffd\uff5e\uff09", "reply": "", "id": 25441161, "name": "\u96f6"}], "last": [], "noMoreReplies": true}, "images": ["http://filestoresg1.beetalkmobile.com:8081/file/e4b9f20f00ef577425d7ebdaae4df59e"], "id": 39286056}, {"postBy": {"location": "\u65b0\u5317\u5e02\u00b7\u53f0\u7063", "utc": 1463618279000, "level": 0, "avatar": "http://filestoresg1.beetalkmobile.com:8081/file/90725105429693196", "name": "\u963f\u5a01"}, "content": "\u770b\u958b\u9ede\uff0c\u96e2\u958b\u9ede\uff0c\u958b\u5fc3\u9ede\u5427\u2026", "urls": [], "replies": {"first": [{"content": "\u6b63\u5728\u7df4\u7fd2\u22ef", "reply": "", "id": 25441490, "name": "\u96f6"}], "last": [], "noMoreReplies": true}, "images": [], "id": 39289824}]}
