{"noMoreComments": true, "cursorEnd": 0, "id": "3637980", "comments": [{"postBy": {"location": "\u65b0\u5317\u5e02\u00b7\u53f0\u7063", "utc": 1462237353000, "level": 0, "avatar": "http://filestoresg1.beetalkmobile.com:8081/file/-4381184384075189440", "name": "\u2652\u8349\u98df\u6c34\u74f6\u7537\u2652"}, "content": "\u590f\u5929\u6216\u5929\u6c23\u71b1\u66f4\u660e\u986f", "urls": [], "replies": {"first": [{"content": "\u671f\u5f85\u590f\u5929\u5230\u4f86", "reply": "", "id": 24600678, "name": "RoseLiu"}], "last": [], "noMoreReplies": true}, "images": [], "id": 37986688}]}
